common_utils/__init__.py
common_utils/base_service.py
common_utils/connections.py
common_utils/constants.py
common_utils/datetime.py
common_utils/decorators.py
common_utils/errors.py
common_utils/exceptions.py
common_utils/logger.py
common_utils/message.py
common_utils/microservices.py
common_utils/pagination.py
common_utils/response.py
common_utils/swagger.py
common_utils/utils.py
common_utils/validators.py
platform_authentication/__init__.py
platform_authentication/apps.py
platform_authentication/errors.py
platform_authentication/middleware.py
platform_authentication-0.0.5.dist-info/LICENSE
platform_authentication-0.0.5.dist-info/METADATA
platform_authentication-0.0.5.dist-info/WHEEL
platform_authentication-0.0.5.dist-info/top_level.txt
platform_authentication-0.0.5.dist-info/RECORD
