Metadata-Version: 2.1
Name: platform-authentication
Version: 0.0.5
Summary: This is an app for managing authnetication in a SaaS product named Platform.
Author: Vishwajeet Kale
Author-email: vishwajeet.kale.v2stech@gmail.com
License: MIT
Classifier: Development Status :: 3 - Alpha
Classifier: Intended Audience :: Developers
Classifier: License :: OSI Approved :: MIT License
Classifier: Programming Language :: Python :: 3
Classifier: Programming Language :: Python :: 3.6
Classifier: Programming Language :: Python :: 3.7
Classifier: Programming Language :: Python :: 3.8
Classifier: Programming Language :: Python :: 3.9
Classifier: Programming Language :: Python :: 3.10
License-File: LICENSE
Requires-Dist: Django >=3.1
Requires-Dist: djangorestframework >=3.11.1
